hsds_api/__init__.py
hsds_api/_hsds_api.py
hsds_api-1.0.0b4.dist-info/METADATA
hsds_api-1.0.0b4.dist-info/WHEEL
hsds_api-1.0.0b4.dist-info/top_level.txt
hsds_api-1.0.0b4.dist-info/RECORD
